instructor_builtsimple/__init__.py
instructor_builtsimple/api.py
instructor_builtsimple/client.py
instructor_builtsimple/extractors.py
instructor_builtsimple/models.py
instructor_builtsimple/py.typed
instructor_builtsimple-0.1.0.dist-info/METADATA
instructor_builtsimple-0.1.0.dist-info/WHEEL
instructor_builtsimple-0.1.0.dist-info/licenses/LICENSE
instructor_builtsimple-0.1.0.dist-info/RECORD
