Metadata-Version: 2.4
Name: instructor-builtsimple
Version: 0.1.0
Summary: Instructor integration for Built-Simple research APIs - structured extraction from PubMed, ArXiv, and Wikipedia
Project-URL: Homepage, https://github.com/built-simple/instructor-builtsimple
Project-URL: Documentation, https://github.com/built-simple/instructor-builtsimple#readme
Project-URL: Repository, https://github.com/built-simple/instructor-builtsimple
Project-URL: Issues, https://github.com/built-simple/instructor-builtsimple/issues
Author-email: Built-Simple <hello@built-simple.ai>
License-Expression: MIT
License-File: LICENSE
Keywords: arxiv,extraction,instructor,llm,pubmed,pydantic,research,structured-output,wikipedia
Classifier: Development Status :: 4 - Beta
Classifier: Intended Audience :: Developers
Classifier: Intended Audience :: Science/Research
Classifier: License :: OSI Approved :: MIT License
Classifier: Programming Language :: Python :: 3
Classifier: Programming Language :: Python :: 3.9
Classifier: Programming Language :: Python :: 3.10
Classifier: Programming Language :: Python :: 3.11
Classifier: Programming Language :: Python :: 3.12
Classifier: Topic :: Scientific/Engineering
Classifier: Topic :: Scientific/Engineering :: Artificial Intelligence
Classifier: Topic :: Scientific/Engineering :: Information Analysis
Requires-Python: >=3.9
Requires-Dist: httpx>=0.25.0
Requires-Dist: instructor>=1.0.0
Requires-Dist: openai>=1.0.0
Requires-Dist: pydantic>=2.0.0
Provides-Extra: all
Requires-Dist: anthropic>=0.18.0; extra == 'all'
Provides-Extra: anthropic
Requires-Dist: anthropic>=0.18.0; extra == 'anthropic'
Provides-Extra: dev
Requires-Dist: pytest-asyncio>=0.21; extra == 'dev'
Requires-Dist: pytest>=7.0; extra == 'dev'
Requires-Dist: python-dotenv>=1.0.0; extra == 'dev'
